gridify/__init__.py
gridify/gridify.py
gridify/processor.py
gridify/py.typed
gridify-0.3.1.dist-info/LICENSE
gridify-0.3.1.dist-info/METADATA
gridify-0.3.1.dist-info/WHEEL
gridify-0.3.1.dist-info/top_level.txt
gridify-0.3.1.dist-info/RECORD
