Metadata-Version: 2.1
Name: gridify
Version: 0.3.1
Summary: Generate a grid of box shaped polygons covering an area
Author-email: RWS Datalab <datalab.codebase@rws.nl>
Project-URL: homepage, https://gitlab.com/rwsdatalab/gridify
Project-URL: repository, https://gitlab.com/rwsdatalab/gridify
Project-URL: changelog, https://gitlab.com/rwsdatalab/gridify/blob/main/CHANGELOG.rst
Keywords: gridify
Classifier: Development Status :: 2 - Pre-Alpha
Classifier: Intended Audience :: Developers
Classifier: Natural Language :: English
Classifier: Programming Language :: Python :: 3
Classifier: Programming Language :: Python :: 3.10
Classifier: Programming Language :: Python :: 3.11
Requires-Python: >=3.10
License-File: LICENSE
Requires-Dist: geopandas
Requires-Dist: rtree
Requires-Dist: numpy
Requires-Dist: shapely
Provides-Extra: dev
Requires-Dist: bandit[toml] ; extra == 'dev'
Requires-Dist: black ; extra == 'dev'
Requires-Dist: flake8 ; extra == 'dev'
Requires-Dist: flake8-bugbear ; extra == 'dev'
Requires-Dist: flake8-comprehensions ; extra == 'dev'
Requires-Dist: flake8-docstrings ; extra == 'dev'
Requires-Dist: flake8-polyfill ; extra == 'dev'
Requires-Dist: isort ; extra == 'dev'
Requires-Dist: mypy ; extra == 'dev'
Requires-Dist: pre-commit ; extra == 'dev'
Requires-Dist: pylint ; extra == 'dev'
Requires-Dist: pytest ; extra == 'dev'
Requires-Dist: pytest-cov ; extra == 'dev'
Requires-Dist: rstcheck[sphinx] ; extra == 'dev'
Requires-Dist: radon ; extra == 'dev'
Requires-Dist: safety ; extra == 'dev'
Requires-Dist: matplotlib ; extra == 'dev'
Provides-Extra: doc
Requires-Dist: pydata-sphinx-theme ; extra == 'doc'
Requires-Dist: sphinx ; extra == 'doc'
Requires-Dist: sphinx-autodoc-typehints ; extra == 'doc'
